depyty/__init__.py
depyty/__main__.py
depyty/autoconf.py
depyty/cli.py
depyty/dependencies.py
depyty/dist_info.py
depyty/environment.py
depyty/environment_standalone.py
depyty/logging.py
depyty/py.typed
depyty/pyproject.py
depyty/source_file_checking.py
depyty/source_file_collection.py
depyty/source_file_module_mapping.py
depyty/uv.py
depyty/reporting/__init__.py
depyty/reporting/abstract.py
depyty/reporting/console.py
depyty/reporting/gitlab.py
depyty-0.2.0.dist-info/METADATA
depyty-0.2.0.dist-info/WHEEL
depyty-0.2.0.dist-info/entry_points.txt
depyty-0.2.0.dist-info/licenses/LICENSE.md
depyty-0.2.0.dist-info/RECORD
