Metadata-Version: 2.4
Name: depyty
Version: 0.2.0
Summary: Enforce proper dependency declaration in shared Python environments
Project-URL: Homepage, https://github.com/NiclasvanEyk/depyty
Project-URL: Documentation, https://github.com/NiclasvanEyk/depyty
Project-URL: Repository, https://github.com/NiclasvanEyk/depyty
Project-URL: Issues, https://github.com/NiclasvanEyk/depyty/issues
Project-URL: Changelog, https://github.com/NiclasvanEyk/depyty/blob/main/CHANGELOG.md
Project-URL: Funding, https://github.com/sponsors/NiclasvanEyk
Author-email: Niclas van Eyk <niclas.eyk@gmail.com>
License: MIT License
License-File: LICENSE.md
Classifier: Intended Audience :: Developers
Classifier: License :: OSI Approved :: MIT License
Classifier: Programming Language :: Python
Classifier: Programming Language :: Python :: 3
Classifier: Programming Language :: Python :: 3 :: Only
Classifier: Programming Language :: Python :: 3.13
Classifier: Topic :: Software Development :: Quality Assurance
Requires-Python: >=3.13
Requires-Dist: packaging>=24.2
